{
  "CitationSubset": [
    "IM"
  ],
  "KeywordList": [
    [
      "Ausdauertraining",
      "Cardiac disease",
      "Herzkrankheit",
      "Malade cardiaque",
      "Sport",
      "aerobic training",
      "cardiovascular prevention",
      "entra\u00eenement d'endurance",
      "exercice physique",
      "kardiovaskul\u00e4re Pr\u00e4vention",
      "koronare Herzkrankheit",
      "sport",
      "sports"
    ]
  ],
  "GeneralNote": [],
  "OtherAbstract": [
    {
      "AbstractText": [
        "Zusammenfassung. Sport zu treiben wird in den Europ\u00e4ischen Richtlinien f\u00fcr die Pr\u00e4vention und initiale Behandlung von vielen kardiovaskul\u00e4ren Erkrankungen, aber auch des metabolischen Syndroms, empfohlen. Letztendlich ist jedoch individuell verschieden, welche physische Aktivit\u00e4t und welche Intensit\u00e4t beziehungsweise Dauer die maximale protektive Wirkung in Bezug auf die Pr\u00e4vention entfaltet. So wurde auch beim k\u00f6rperlichen Training ein J-Kurven-Zusammenhang postuliert, mit der Annahme, dass zu viel Sport gleich sch\u00e4dlich oder potenziell gar noch sch\u00e4dlicher sei wie zu wenig Sport. In diesem Review versuchen wir die Frage zu beantworten, wie viel und welcher Sport optimal f\u00fcr Herzpatienten ist."
      ]
    }
  ],
  "SpaceFlightMission": [],
  "OtherID": [],
  "InvestigatorList": [],
  "PMID": "29788848",
  "DateCompleted": {
    "Year": "2018",
    "Month": "09",
    "Day": "06"
  },
  "DateRevised": {
    "Year": "2018",
    "Month": "09",
    "Day": "06"
  },
  "Article": {
    "ArticleDate": [],
    "Language": [
      "ger"
    ],
    "ELocationID": [
      "10.1024/1661-8157/a002993"
    ],
    "Journal": {
      "ISSN": "1661-8157",
      "JournalIssue": {
        "Volume": "107",
        "Issue": "11",
        "PubDate": {
          "Year": "2018"
        }
      },
      "Title": "Praxis",
      "ISOAbbreviation": "Praxis (Bern 1994)"
    },
    "ArticleTitle": "[Sports in Patients with Heart Disease: What Should Be Recommended?].",
    "Pagination": {
      "StartPage": "585",
      "EndPage": "591",
      "MedlinePgn": "585-591"
    },
    "Abstract": {
      "AbstractText": [
        "Sports in Patients with Heart Disease: What Should Be Recommended? Abstract. Sports is recommended in the European guidelines for the prevention and initial treatment of many cardiovascular diseases as well as the metabolic syndrome. However, the individually recommended intensity and duration of physical activity that unfolds the maximal protective effects in terms of prevention, largely differs. Indeed, a J-curve relationship with regard to exercise training has been postulated, with the assumption that too much sports is equally harmful or potentially even more harmful than too little sports. In this review, we try to answer the question of how much and which sports is optimal for cardiac patients."
      ]
    },
    "AuthorList": [
      {
        "Identifier": [],
        "AffiliationInfo": [
          {
            "Identifier": [],
            "Affiliation": "1 Universit\u00e4res Herzzentrum Z\u00fcrich, Klinik f\u00fcr Kardiologie, Universit\u00e4tsspital Z\u00fcrich."
          }
        ],
        "LastName": "Rossi",
        "ForeName": "Valentina Alice",
        "Initials": "VA"
      },
      {
        "Identifier": [],
        "AffiliationInfo": [
          {
            "Identifier": [],
            "Affiliation": "1 Universit\u00e4res Herzzentrum Z\u00fcrich, Klinik f\u00fcr Kardiologie, Universit\u00e4tsspital Z\u00fcrich."
          }
        ],
        "LastName": "Schmied",
        "ForeName": "Christian M",
        "Initials": "CM"
      },
      {
        "Identifier": [],
        "AffiliationInfo": [
          {
            "Identifier": [],
            "Affiliation": "1 Universit\u00e4res Herzzentrum Z\u00fcrich, Klinik f\u00fcr Kardiologie, Universit\u00e4tsspital Z\u00fcrich."
          }
        ],
        "LastName": "Niederseer",
        "ForeName": "David",
        "Initials": "D"
      }
    ],
    "PublicationTypeList": [
      "Journal Article",
      "Review"
    ],
    "VernacularTitle": "Sport bei Herzpatienten: Was soll man empfehlen?"
  },
  "MedlineJournalInfo": {
    "Country": "Switzerland",
    "MedlineTA": "Praxis (Bern 1994)",
    "NlmUniqueID": "101468093",
    "ISSNLinking": "1661-8157"
  },
  "MeshHeadingList": [
    {
      "QualifierName": [
        "etiology",
        "prevention & control"
      ],
      "DescriptorName": "Death, Sudden, Cardiac"
    },
    {
      "QualifierName": [],
      "DescriptorName": "Decision Making"
    },
    {
      "QualifierName": [],
      "DescriptorName": "Europe"
    },
    {
      "QualifierName": [],
      "DescriptorName": "Guideline Adherence"
    },
    {
      "QualifierName": [
        "etiology",
        "prevention & control",
        "rehabilitation"
      ],
      "DescriptorName": "Heart Diseases"
    },
    {
      "QualifierName": [],
      "DescriptorName": "Physical Endurance"
    },
    {
      "QualifierName": [],
      "DescriptorName": "Precision Medicine"
    },
    {
      "QualifierName": [],
      "DescriptorName": "Primary Prevention"
    },
    {
      "QualifierName": [],
      "DescriptorName": "Risk Factors"
    },
    {
      "QualifierName": [],
      "DescriptorName": "Secondary Prevention"
    },
    {
      "QualifierName": [],
      "DescriptorName": "Sports"
    }
  ]
}