{
  "CitationSubset": [
    "IM"
  ],
  "KeywordList": [],
  "GeneralNote": [],
  "OtherAbstract": [],
  "SpaceFlightMission": [],
  "OtherID": [],
  "InvestigatorList": [],
  "PMID": "932984",
  "DateCompleted": {
    "Year": "1976",
    "Month": "09",
    "Day": "01"
  },
  "DateRevised": {
    "Year": "2019",
    "Month": "07",
    "Day": "10"
  },
  "Article": {
    "ArticleDate": [],
    "Language": [
      "eng"
    ],
    "ELocationID": [],
    "Journal": {
      "ISSN": "0022-3549",
      "JournalIssue": {
        "Volume": "65",
        "Issue": "6",
        "PubDate": {
          "Year": "1976",
          "Month": "Jun"
        }
      },
      "Title": "Journal of pharmaceutical sciences",
      "ISOAbbreviation": "J Pharm Sci"
    },
    "ArticleTitle": "Simultaneous quantitative GLC determination of chlorpheniramine maleate and phenylpropanolamine hydrochloride in a cold tablet preparation.",
    "Pagination": {
      "StartPage": "924",
      "EndPage": "925",
      "MedlinePgn": "924-5"
    },
    "Abstract": {
      "AbstractText": [
        "A GLC method was developed for the simultaneous determinations of chlorpheniramine maleate and phenylpropanolamine hydrocholride in a cold tablet preparation containing a large amount of aspirin. The method utilizes a solid sampling device to eliminate interference from solvent, and it is rapid and precise. The total analysis time is less than 1.5 hr, thereby permitting its use for quality control purposes."
      ]
    },
    "AuthorList": [
      {
        "Identifier": [],
        "AffiliationInfo": [],
        "LastName": "Madsen",
        "ForeName": "R E",
        "Initials": "RE"
      },
      {
        "Identifier": [],
        "AffiliationInfo": [],
        "LastName": "Magin",
        "ForeName": "D F",
        "Initials": "DF"
      }
    ],
    "PublicationTypeList": [
      "Journal Article"
    ]
  },
  "MedlineJournalInfo": {
    "Country": "United States",
    "MedlineTA": "J Pharm Sci",
    "NlmUniqueID": "2985195R",
    "ISSNLinking": "0022-3549"
  },
  "ChemicalList": [
    {
      "RegistryNumber": "0",
      "NameOfSubstance": "Tablets"
    },
    {
      "RegistryNumber": "33RU150WUN",
      "NameOfSubstance": "Phenylpropanolamine"
    },
    {
      "RegistryNumber": "3U6IO1965U",
      "NameOfSubstance": "Chlorpheniramine"
    },
    {
      "RegistryNumber": "R16CO5Y76E",
      "NameOfSubstance": "Aspirin"
    }
  ],
  "MeshHeadingList": [
    {
      "QualifierName": [],
      "DescriptorName": "Aspirin"
    },
    {
      "QualifierName": [
        "analysis"
      ],
      "DescriptorName": "Chlorpheniramine"
    },
    {
      "QualifierName": [],
      "DescriptorName": "Chromatography, Gas"
    },
    {
      "QualifierName": [
        "drug therapy"
      ],
      "DescriptorName": "Common Cold"
    },
    {
      "QualifierName": [
        "analysis"
      ],
      "DescriptorName": "Phenylpropanolamine"
    },
    {
      "QualifierName": [],
      "DescriptorName": "Tablets"
    }
  ]
}