{
  "CitationSubset": [
    "IM"
  ],
  "KeywordList": [],
  "GeneralNote": [],
  "OtherAbstract": [],
  "SpaceFlightMission": [],
  "OtherID": [],
  "InvestigatorList": [],
  "PMID": "26012807",
  "DateCompleted": {
    "Year": "2015",
    "Month": "08",
    "Day": "25"
  },
  "DateRevised": {
    "Year": "2015",
    "Month": "05",
    "Day": "27"
  },
  "Article": {
    "ArticleDate": [],
    "Language": [
      "ger"
    ],
    "ELocationID": [
      "10.1007/s15006-015-3064-8"
    ],
    "Journal": {
      "ISSN": "1438-3276",
      "JournalIssue": {
        "Volume": "157",
        "Issue": "9",
        "PubDate": {
          "Year": "2015",
          "Month": "May",
          "Day": "13"
        }
      },
      "Title": "MMW Fortschritte der Medizin",
      "ISOAbbreviation": "MMW Fortschr Med"
    },
    "ArticleTitle": "[Prescribe sports - but in the proper dosage!].",
    "Pagination": {
      "StartPage": "20",
      "EndPage": "24",
      "MedlinePgn": "20-2, 24"
    },
    "AuthorList": [
      {
        "Identifier": [],
        "AffiliationInfo": [
          {
            "Identifier": [],
            "Affiliation": ", ."
          }
        ],
        "LastName": "F\u00fceael",
        "ForeName": "H S",
        "Initials": "HS"
      }
    ],
    "PublicationTypeList": [
      "News"
    ],
    "VernacularTitle": "Verordnen Sie Sport - aber richtig dosiert!"
  },
  "MedlineJournalInfo": {
    "Country": "Germany",
    "MedlineTA": "MMW Fortschr Med",
    "NlmUniqueID": "100893959",
    "ISSNLinking": "1438-3276"
  },
  "MeshHeadingList": [
    {
      "QualifierName": [
        "immunology",
        "prevention & control"
      ],
      "DescriptorName": "Cardiovascular Diseases"
    },
    {
      "QualifierName": [
        "immunology",
        "prevention & control"
      ],
      "DescriptorName": "Common Cold"
    },
    {
      "QualifierName": [
        "physiology"
      ],
      "DescriptorName": "Exercise"
    },
    {
      "QualifierName": [],
      "DescriptorName": "Exercise Test"
    },
    {
      "QualifierName": [],
      "DescriptorName": "Humans"
    },
    {
      "QualifierName": [
        "immunology"
      ],
      "DescriptorName": "Immune Tolerance"
    },
    {
      "QualifierName": [
        "immunology"
      ],
      "DescriptorName": "Immunity, Cellular"
    },
    {
      "QualifierName": [
        "immunology",
        "prevention & control"
      ],
      "DescriptorName": "Influenza, Human"
    },
    {
      "QualifierName": [
        "physiology"
      ],
      "DescriptorName": "Physical Fitness"
    },
    {
      "QualifierName": [
        "physiology"
      ],
      "DescriptorName": "Sports"
    }
  ]
}