{
  "CitationSubset": [
    "IM"
  ],
  "KeywordList": [],
  "GeneralNote": [],
  "OtherAbstract": [],
  "SpaceFlightMission": [],
  "OtherID": [],
  "InvestigatorList": [],
  "PMID": "3738506",
  "DateCompleted": {
    "Year": "1986",
    "Month": "09",
    "Day": "17"
  },
  "DateRevised": {
    "Year": "2007",
    "Month": "03",
    "Day": "19"
  },
  "Article": {
    "ArticleDate": [],
    "Language": [
      "eng"
    ],
    "ELocationID": [],
    "Journal": {
      "ISSN": "0036-8075",
      "JournalIssue": {
        "Volume": "233",
        "Issue": "4765",
        "PubDate": {
          "Year": "1986",
          "Month": "Aug",
          "Day": "15"
        }
      },
      "Title": "Science (New York, N.Y.)",
      "ISOAbbreviation": "Science"
    },
    "ArticleTitle": "Depression research advances, treatment lags.",
    "Pagination": {
      "StartPage": "723",
      "EndPage": "726",
      "MedlinePgn": "723-6"
    },
    "AuthorList": [
      {
        "Identifier": [],
        "AffiliationInfo": [],
        "LastName": "Holden",
        "ForeName": "C",
        "Initials": "C"
      }
    ],
    "PublicationTypeList": [
      "News"
    ]
  },
  "MedlineJournalInfo": {
    "Country": "United States",
    "MedlineTA": "Science",
    "NlmUniqueID": "0404511",
    "ISSNLinking": "0036-8075"
  },
  "MeshHeadingList": [
    {
      "QualifierName": [
        "classification",
        "etiology",
        "therapy"
      ],
      "DescriptorName": "Depression"
    },
    {
      "QualifierName": [
        "classification",
        "etiology",
        "therapy"
      ],
      "DescriptorName": "Depressive Disorder"
    },
    {
      "QualifierName": [],
      "DescriptorName": "Humans"
    },
    {
      "QualifierName": [],
      "DescriptorName": "National Institutes of Health (U.S.)"
    },
    {
      "QualifierName": [],
      "DescriptorName": "United States"
    }
  ]
}