{
  "CitationSubset": [
    "IM"
  ],
  "KeywordList": [],
  "GeneralNote": [],
  "OtherAbstract": [],
  "SpaceFlightMission": [],
  "OtherID": [],
  "InvestigatorList": [],
  "PMID": "7148639",
  "DateCompleted": {
    "Year": "1983",
    "Month": "01",
    "Day": "27"
  },
  "DateRevised": {
    "Year": "2013",
    "Month": "11",
    "Day": "21"
  },
  "Article": {
    "ArticleDate": [],
    "Language": [
      "eng"
    ],
    "ELocationID": [],
    "Journal": {
      "ISSN": "0002-838X",
      "JournalIssue": {
        "Volume": "26",
        "Issue": "6",
        "PubDate": {
          "Year": "1982",
          "Month": "Dec"
        }
      },
      "Title": "American family physician",
      "ISOAbbreviation": "Am Fam Physician"
    },
    "ArticleTitle": "Depression.",
    "Pagination": {
      "StartPage": "156",
      "EndPage": "162",
      "MedlinePgn": "156-62"
    },
    "AuthorList": [
      {
        "Identifier": [],
        "AffiliationInfo": [],
        "LastName": "Davis",
        "ForeName": "D",
        "Initials": "D"
      },
      {
        "Identifier": [],
        "AffiliationInfo": [],
        "LastName": "Chapel",
        "ForeName": "J L",
        "Initials": "JL"
      }
    ],
    "PublicationTypeList": [
      "Journal Article"
    ]
  },
  "MedlineJournalInfo": {
    "Country": "United States",
    "MedlineTA": "Am Fam Physician",
    "NlmUniqueID": "1272646",
    "ISSNLinking": "0002-838X"
  },
  "ChemicalList": [
    {
      "RegistryNumber": "0",
      "NameOfSubstance": "Antidepressive Agents"
    },
    {
      "RegistryNumber": "0",
      "NameOfSubstance": "Antidepressive Agents, Tricyclic"
    },
    {
      "RegistryNumber": "0",
      "NameOfSubstance": "Monoamine Oxidase Inhibitors"
    },
    {
      "RegistryNumber": "9FN79X2M3F",
      "NameOfSubstance": "Lithium"
    }
  ],
  "MeshHeadingList": [
    {
      "QualifierName": [],
      "DescriptorName": "Adult"
    },
    {
      "QualifierName": [],
      "DescriptorName": "Aged"
    },
    {
      "QualifierName": [
        "therapeutic use"
      ],
      "DescriptorName": "Antidepressive Agents"
    },
    {
      "QualifierName": [
        "therapeutic use"
      ],
      "DescriptorName": "Antidepressive Agents, Tricyclic"
    },
    {
      "QualifierName": [
        "classification",
        "diagnosis",
        "therapy"
      ],
      "DescriptorName": "Depression"
    },
    {
      "QualifierName": [
        "diagnosis"
      ],
      "DescriptorName": "Depressive Disorder"
    },
    {
      "QualifierName": [],
      "DescriptorName": "Female"
    },
    {
      "QualifierName": [],
      "DescriptorName": "Humans"
    },
    {
      "QualifierName": [
        "therapeutic use"
      ],
      "DescriptorName": "Lithium"
    },
    {
      "QualifierName": [],
      "DescriptorName": "Male"
    },
    {
      "QualifierName": [],
      "DescriptorName": "Middle Aged"
    },
    {
      "QualifierName": [
        "therapeutic use"
      ],
      "DescriptorName": "Monoamine Oxidase Inhibitors"
    },
    {
      "QualifierName": [],
      "DescriptorName": "Psychotherapy"
    }
  ]
}